libparse.so
composeparser/__init__.py
composeparser/parse.py
ComposeParser-0.0.4.dist-info/LICENSE
ComposeParser-0.0.4.dist-info/METADATA
ComposeParser-0.0.4.dist-info/NOTICE
ComposeParser-0.0.4.dist-info/WHEEL
ComposeParser-0.0.4.dist-info/top_level.txt
ComposeParser-0.0.4.dist-info/RECORD
