Metadata-Version: 2.1
Name: ComposeParser
Version: 0.0.4
Summary: Docker Compose Parser
Home-page: UNKNOWN
Author: Uchenic
Author-email: uchenic@protonmail.com
License: UNKNOWN
Platform: UNKNOWN
License-File: LICENSE
License-File: NOTICE
